app/__init__.py
app/config.py
app/main.py
app/backends/__init__.py
app/backends/base.py
app/backends/factory.py
app/backends/mlx_backend.py
app/backends/mlx_reranker_backend.py
app/backends/torch_backend.py
app/backends/torch_reranker_backend.py
app/models/__init__.py
app/models/cohere_models.py
app/models/requests.py
app/models/responses.py
app/routers/__init__.py
app/routers/cohere_router.py
app/routers/embedding_router.py
app/routers/health_router.py
app/routers/openai_router.py
app/routers/reranking_router.py
app/routers/tei_router.py
app/services/__init__.py
app/services/embedding_service.py
app/services/reranking_service.py
app/utils/__init__.py
app/utils/benchmark.py
app/utils/device.py
app/utils/logger.py
app/utils/logging.py
app/utils/model_metadata.py
app/utils/text_utils.py
embed_rerank-1.5.1.dist-info/METADATA
embed_rerank-1.5.1.dist-info/WHEEL
embed_rerank-1.5.1.dist-info/entry_points.txt
embed_rerank-1.5.1.dist-info/licenses/LICENSE
embed_rerank-1.5.1.dist-info/RECORD
