Metadata-Version: 2.4
Name: embed-rerank
Version: 1.5.1
Summary: Single Model Embedding & Reranker API with Apple Silicon acceleration
Project-URL: Documentation, https://github.com/joonsoo-me/embed-rerank#readme
Project-URL: Issues, https://github.com/joonsoo-me/embed-rerank/issues
Project-URL: Source, https://github.com/joonsoo-me/embed-rerank
Author-email: joonsoo-me <bear8203@gmail.com>
License-Expression: MIT
License-File: LICENSE
Keywords: apple-silicon,embeddings,fastapi,mlx,reranking
Classifier: Development Status :: 4 - Beta
Classifier: Framework :: FastAPI
Classifier: Intended Audience :: Developers
Classifier: License :: OSI Approved :: MIT License
Classifier: Programming Language :: Python :: 3.13
Classifier: Programming Language :: Python :: Implementation :: CPython
Classifier: Topic :: Scientific/Engineering :: Artificial Intelligence
Requires-Python: >=3.13
Requires-Dist: fastapi>=0.104.0
Requires-Dist: httpx>=0.25.0
Requires-Dist: numpy>=1.24.0
Requires-Dist: prometheus-client
Requires-Dist: pydantic-settings>=2.0.0
Requires-Dist: pydantic>=2.0.0
Requires-Dist: python-dotenv
Requires-Dist: python-multipart
Requires-Dist: sentence-transformers>=2.2.0
Requires-Dist: structlog
Requires-Dist: torch>=2.0.0
Requires-Dist: transformers>=4.30.0
Requires-Dist: uvicorn[standard]>=0.24.0
Provides-Extra: dev
Requires-Dist: bandit[toml]>=1.7.5; extra == 'dev'
Requires-Dist: black>=23.0.0; extra == 'dev'
Requires-Dist: flake8>=6.0.0; extra == 'dev'
Requires-Dist: isort>=5.12.0; extra == 'dev'
Requires-Dist: locust>=2.16.0; extra == 'dev'
Requires-Dist: mypy>=1.5.0; extra == 'dev'
Requires-Dist: pre-commit>=3.0.0; extra == 'dev'
Requires-Dist: pytest-asyncio>=0.21.0; extra == 'dev'
Requires-Dist: pytest-cov>=4.1.0; extra == 'dev'
Requires-Dist: pytest-mock>=3.11.0; extra == 'dev'
Requires-Dist: pytest>=7.4.0; extra == 'dev'
Requires-Dist: safety>=2.3.0; extra == 'dev'
Requires-Dist: types-requests>=2.31.0; extra == 'dev'
Provides-Extra: mlx
Requires-Dist: mlx-lm>=0.2.0; (sys_platform == 'darwin') and extra == 'mlx'
Requires-Dist: mlx>=0.4.0; (sys_platform == 'darwin') and extra == 'mlx'
